llama_index/py.typed
llama_index/vector_stores/moorcheh/__init__.py
llama_index/vector_stores/moorcheh/base.py
llama_index/vector_stores/moorcheh/utils.py
llama_index_vector_stores_moorcheh-0.2.1.dist-info/METADATA
llama_index_vector_stores_moorcheh-0.2.1.dist-info/WHEEL
llama_index_vector_stores_moorcheh-0.2.1.dist-info/RECORD
