Metadata-Version: 2.4
Name: llama-index-vector-stores-moorcheh
Version: 0.2.1
Summary: llama-index vector_stores moorcheh integration
Author: EdgeAI Innovations
License-Expression: MIT
Requires-Python: <4.0,>=3.10
Requires-Dist: llama-index-core<0.15,>=0.13.0
Requires-Dist: llama-index-llms-openai>=0.1.0
Requires-Dist: moorcheh-sdk<2.1.0,>=0.1.0
Requires-Dist: openai>=1.0.0
